mcp_optimizer/__init__.py
mcp_optimizer/__main__.py
mcp_optimizer/config.py
mcp_optimizer/main.py
mcp_optimizer/mcp_server.py
mcp_optimizer/schemas/__init__.py
mcp_optimizer/schemas/base.py
mcp_optimizer/schemas/problem_schemas.py
mcp_optimizer/solvers/__init__.py
mcp_optimizer/solvers/fallback_solver.py
mcp_optimizer/solvers/ortools_solver.py
mcp_optimizer/solvers/pulp_solver.py
mcp_optimizer/tools/__init__.py
mcp_optimizer/tools/assignment.py
mcp_optimizer/tools/financial.py
mcp_optimizer/tools/integer_programming.py
mcp_optimizer/tools/knapsack.py
mcp_optimizer/tools/linear_programming.py
mcp_optimizer/tools/production.py
mcp_optimizer/tools/routing.py
mcp_optimizer/tools/scheduling.py
mcp_optimizer/tools/validation.py
mcp_optimizer/utils/__init__.py
mcp_optimizer/utils/resource_monitor.py
mcp_optimizer-0.4.1.dist-info/METADATA
mcp_optimizer-0.4.1.dist-info/WHEEL
mcp_optimizer-0.4.1.dist-info/entry_points.txt
mcp_optimizer-0.4.1.dist-info/licenses/LICENSE
mcp_optimizer-0.4.1.dist-info/RECORD
