Metadata-Version: 2.4
Name: mcp-optimizer
Version: 0.4.1
Summary: Mathematical optimization MCP server with PuLP and OR-Tools support
Project-URL: Homepage, https://github.com/dmitryanchikov/mcp-optimizer
Project-URL: Repository, https://github.com/dmitryanchikov/mcp-optimizer
Project-URL: Documentation, https://github.com/dmitryanchikov/mcp-optimizer#readme
Project-URL: Bug Tracker, https://github.com/dmitryanchikov/mcp-optimizer/issues
Author-email: Dmitry Anchikov <dmitry.anchikov@gmail.com>
License: MIT
License-File: LICENSE
Keywords: linear-programming,mcp,operations-research,optimization,ortools,pulp
Classifier: Development Status :: 4 - Beta
Classifier: Intended Audience :: Developers
Classifier: Intended Audience :: Science/Research
Classifier: License :: OSI Approved :: MIT License
Classifier: Operating System :: OS Independent
Classifier: Programming Language :: Python :: 3
Classifier: Programming Language :: Python :: 3.11
Classifier: Programming Language :: Python :: 3.12
Classifier: Topic :: Scientific/Engineering :: Mathematics
Classifier: Topic :: Software Development :: Libraries :: Python Modules
Requires-Python: >=3.11
Requires-Dist: fastmcp>=2.5.0
Requires-Dist: ortools>=9.8.0
Requires-Dist: psutil>=5.9.0
Requires-Dist: pulp>=2.8.0
Requires-Dist: pydantic-settings>=2.1.0
Requires-Dist: pydantic>=2.5.0
Requires-Dist: uvicorn[standard]>=0.24.0
Provides-Extra: dev
Requires-Dist: bandit>=1.7.5; extra == 'dev'
Requires-Dist: mypy>=1.7.0; extra == 'dev'
Requires-Dist: pytest-asyncio>=0.26.0; extra == 'dev'
Requires-Dist: pytest-cov>=6.1.1; extra == 'dev'
Requires-Dist: pytest>=7.4.0; extra == 'dev'
Requires-Dist: ruff>=0.11.11; extra == 'dev'
Provides-Extra: examples
Requires-Dist: numpy>=1.24.0; extra == 'examples'
Requires-Dist: pandas>=2.0.0; extra == 'examples'
Requires-Dist: plotly>=5.17.0; extra == 'examples'
Requires-Dist: streamlit>=1.28.0; extra == 'examples'
Provides-Extra: stable
Requires-Dist: fastmcp==2.7.0; extra == 'stable'
Requires-Dist: sse-starlette==2.2.1; extra == 'stable'
Requires-Dist: starlette==0.46.1; extra == 'stable'
Requires-Dist: uvicorn==0.34.0; extra == 'stable'
